ibkr_engine_osy/__init__.py
ibkr_engine_osy/client.py
ibkr_engine_osy/connection.py
ibkr_engine_osy/contracts.py
ibkr_engine_osy/decoder.py
ibkr_engine_osy/enums.py
ibkr_engine_osy/ib.py
ibkr_engine_osy/logger.py
ibkr_engine_osy/main.py
ibkr_engine_osy/objects.py
ibkr_engine_osy/order.py
ibkr_engine_osy/ticker.py
ibkr_engine_osy/utils.py
ibkr_engine_osy/wrapper.py
ibkr_engine_osy/client_2/__init__.py
ibkr_engine_osy/client_2/base_client.py
ibkr_engine_osy/client_2/client.py
ibkr_engine_osy/client_2/client_connection.py
ibkr_engine_osy/client_2/client_connection_socket.py
ibkr_engine_osy/client_2/client_events.py
ibkr_engine_osy/client_2/client_stats.py
ibkr_engine_osy-0.0.1.dist-info/METADATA
ibkr_engine_osy-0.0.1.dist-info/WHEEL
ibkr_engine_osy-0.0.1.dist-info/licenses/LICENSE
ibkr_engine_osy-0.0.1.dist-info/RECORD
